<?xml version='1.0' encoding='utf-8'?>
<TextureAtlas imagePath="Dialogthing.png">
<SubTexture name="gangletalk0000" x="371" y="0" width="95" height="142" frameX="-46" frameY="-39" frameWidth="1280" frameHeight="720" />
<SubTexture name="ganglenormal0000" x="257" y="187" width="82" height="143" frameX="-52" frameY="-41" frameWidth="1280" frameHeight="720" />
<SubTexture name="ganglesad0000" x="163" y="187" width="94" height="144" frameX="-38" frameY="-41" frameWidth="1280" frameHeight="720" />
<SubTexture name="jaxnormal0000" x="149" y="0" width="111" height="177" frameX="-46" frameY="-5" frameWidth="1280" frameHeight="720" />
<SubTexture name="jaxswear0000" x="260" y="0" width="111" height="177" frameX="-46" frameY="-5" frameWidth="1280" frameHeight="720" />
<SubTexture name="jaxpensativo0000" x="466" y="135" width="112" height="132" frameX="-28" frameY="-50" frameWidth="1280" frameHeight="720" />
<SubTexture name="jaxjueputaporquereganasagangle0000" x="111" y="333" width="121" height="126" frameX="-30" frameY="-55" frameWidth="1280" frameHeight="720" />
<SubTexture name="gumiguo0000" x="0" y="333" width="111" height="129" frameX="-41" frameY="-55" frameWidth="1280" frameHeight="720" />
<SubTexture name="guminojado0000" x="232" y="333" width="112" height="119" frameX="-40" frameY="-65" frameWidth="1280" frameHeight="720" />
<SubTexture name="ragathagritaJAXXX0000" x="466" y="0" width="116" height="135" frameX="-43" frameY="-53" frameWidth="1280" frameHeight="720" />
<SubTexture name="Valle0000" x="0" y="187" width="163" height="146" frameX="-18" frameY="-38" frameWidth="1280" frameHeight="720" />
<SubTexture name="Precipisio0000" x="0" y="0" width="149" height="187" frameX="-35" frameY="-6" frameWidth="1280" frameHeight="720" />
<SubTexture name="Camion0000" x="344" y="333" width="154" height="75" frameX="-35" frameY="-106" frameWidth="1280" frameHeight="720" />
</TextureAtlas>
