<?xml version="1.0" encoding="UTF-8"?>
<!--
Created with Free texture packer v0.6.7 http://free-tex-packer.com
-->
<TextureAtlas imagePath="Pomni.png" width="3514.5" height="3795.5">
  <SubTexture name="Up0001.png" x="0.0" y="0.0"  width="705.0" height="497.0" frameX="-49.5" frameY="-17.5" frameWidth="960.0" frameHeight="540.0"/>
  <SubTexture name="Up0004.png" x="0.0" y="497.0"  width="705.0" height="486.0" frameX="-49.5" frameY="-28.5" frameWidth="960.0" frameHeight="540.0"/>
  <SubTexture name="Up0007.png" x="0.0" y="983.0"  width="705.0" height="484.5" frameX="-49.5" frameY="-30.0" frameWidth="960.0" frameHeight="540.0"/>
  <SubTexture name="Right0002.png" x="0.0" y="1467.5"  width="705.0" height="469.5" frameX="-49.5" frameY="-45.0" frameWidth="960.0" frameHeight="540.0"/>
  <SubTexture name="Right0005.png" x="0.0" y="1937.0"  width="705.0" height="466.5" frameX="-49.5" frameY="-48.0" frameWidth="960.0" frameHeight="540.0"/>
  <SubTexture name="Left0002.png" x="0.0" y="2403.5"  width="705.0" height="465.5" frameX="-49.5" frameY="-49.0" frameWidth="960.0" frameHeight="540.0"/>
  <SubTexture name="Left0005.png" x="0.0" y="2869.0"  width="705.0" height="463.5" frameX="-49.5" frameY="-51.0" frameWidth="960.0" frameHeight="540.0"/>
  <SubTexture name="Idle0002.png" x="0.0" y="3332.5"  width="705.0" height="463.0" frameX="-49.5" frameY="-51.5" frameWidth="960.0" frameHeight="540.0"/>
  <SubTexture name="Up0002.png" x="705.0" y="0.0"  width="696.5" height="494.5" frameX="-58.0" frameY="-20.0" frameWidth="960.0" frameHeight="540.0"/>
  <SubTexture name="Up0003.png" x="705.0" y="494.5"  width="703.0" height="484.0" frameX="-51.5" frameY="-30.5" frameWidth="960.0" frameHeight="540.0"/>
  <SubTexture name="JaxMe!#$%EnTuMadre0002.png" x="1401.5" y="0.0"  width="705.0" height="463.0" frameX="-49.5" frameY="-51.5" frameWidth="960.0" frameHeight="540.0"/>
  <SubTexture name="miss0002.png" x="705.0" y="978.5"  width="705.0" height="463.0" frameX="-49.5" frameY="-51.5" frameWidth="960.0" frameHeight="540.0"/>
  <SubTexture name="Down0003.png" x="1408.0" y="463.0"  width="705.0" height="456.5" frameX="-49.5" frameY="-58.0" frameWidth="960.0" frameHeight="540.0"/>
  <SubTexture name="Down0006.png" x="2106.5" y="0.0"  width="705.0" height="455.5" frameX="-49.5" frameY="-59.0" frameWidth="960.0" frameHeight="540.0"/>
  <SubTexture name="Up0006.png" x="705.0" y="1441.5"  width="703.0" height="482.5" frameX="-51.5" frameY="-32.0" frameWidth="960.0" frameHeight="540.0"/>
  <SubTexture name="Up0005.png" x="1408.0" y="1441.5"  width="696.5" height="482.5" frameX="-58.0" frameY="-32.0" frameWidth="960.0" frameHeight="540.0"/>
  <SubTexture name="Right0001.png" x="1410.0" y="919.5"  width="703.0" height="473.0" frameX="-51.5" frameY="-41.5" frameWidth="960.0" frameHeight="540.0"/>
  <SubTexture name="Right0007.png" x="2104.5" y="1392.5"  width="703.0" height="470.0" frameX="-51.5" frameY="-44.5" frameWidth="960.0" frameHeight="540.0"/>
  <SubTexture name="Right0004.png" x="2113.0" y="455.5"  width="703.0" height="469.5" frameX="-51.5" frameY="-45.0" frameWidth="960.0" frameHeight="540.0"/>
  <SubTexture name="Down0002.png" x="2811.5" y="0.0"  width="703.0" height="451.5" frameX="-51.5" frameY="-63.0" frameWidth="960.0" frameHeight="540.0"/>
  <SubTexture name="Idle0001.png" x="2113.0" y="925.0"  width="703.0" height="467.5" frameX="-51.5" frameY="-47.0" frameWidth="960.0" frameHeight="540.0"/>
  <SubTexture name="JaxMe!#$%EnTuMadre0001.png" x="2104.5" y="1862.5"  width="703.0" height="467.5" frameX="-51.5" frameY="-47.0" frameWidth="960.0" frameHeight="540.0"/>
  <SubTexture name="Left0001.png" x="705.0" y="1924.0"  width="703.0" height="467.5" frameX="-51.5" frameY="-47.0" frameWidth="960.0" frameHeight="540.0"/>
  <SubTexture name="Right0003.png" x="1408.0" y="1924.0"  width="696.5" height="464.5" frameX="-58.0" frameY="-50.0" frameWidth="960.0" frameHeight="540.0"/>
  <SubTexture name="miss0001.png" x="2104.5" y="2330.0"  width="703.0" height="467.5" frameX="-51.5" frameY="-47.0" frameWidth="960.0" frameHeight="540.0"/>
  <SubTexture name="Left0004.png" x="705.0" y="2391.5"  width="703.0" height="465.5" frameX="-51.5" frameY="-49.0" frameWidth="960.0" frameHeight="540.0"/>
  <SubTexture name="Right0006.png" x="1408.0" y="2388.5"  width="696.5" height="464.5" frameX="-58.0" frameY="-50.0" frameWidth="960.0" frameHeight="540.0"/>
  <SubTexture name="Left0007.png" x="2104.5" y="2797.5"  width="703.0" height="464.5" frameX="-51.5" frameY="-50.0" frameWidth="960.0" frameHeight="540.0"/>
  <SubTexture name="Left0003.png" x="705.0" y="2857.0"  width="696.5" height="463.5" frameX="-58.0" frameY="-51.0" frameWidth="960.0" frameHeight="540.0"/>
  <SubTexture name="Left0006.png" x="1401.5" y="2857.0"  width="696.5" height="463.0" frameX="-58.0" frameY="-51.5" frameWidth="960.0" frameHeight="540.0"/>
  <SubTexture name="Down0005.png" x="2098.0" y="3262.0"  width="703.0" height="456.0" frameX="-51.5" frameY="-58.5" frameWidth="960.0" frameHeight="540.0"/>
  <SubTexture name="Down0004.png" x="1401.5" y="3320.0"  width="696.5" height="462.5" frameX="-58.0" frameY="-52.0" frameWidth="960.0" frameHeight="540.0"/>
  <SubTexture name="Idle0003.png" x="705.0" y="3320.5"  width="696.5" height="462.0" frameX="-58.0" frameY="-52.5" frameWidth="960.0" frameHeight="540.0"/>
  <SubTexture name="JaxMe!#$%EnTuMadre0003.png" x="2801.0" y="3262.0"  width="696.5" height="462.0" frameX="-58.0" frameY="-52.5" frameWidth="960.0" frameHeight="540.0"/>
  <SubTexture name="miss0003.png" x="2807.5" y="1392.5"  width="696.5" height="462.0" frameX="-58.0" frameY="-52.5" frameWidth="960.0" frameHeight="540.0"/>
  <SubTexture name="Down0007.png" x="2816.0" y="451.5"  width="696.5" height="461.0" frameX="-58.0" frameY="-53.5" frameWidth="960.0" frameHeight="540.0"/>
  <SubTexture name="Down0001.png" x="2816.0" y="912.5"  width="696.5" height="455.5" frameX="-58.0" frameY="-59.0" frameWidth="960.0" frameHeight="540.0"/>
</TextureAtlas>