{
	"animations": [
		{
			"offsets": [
				150,
				500
			],
			"loop": false,
			"anim": "idle",
			"fps": 24,
			"name": "Bon Idle Dance",
			"indices": []
		},
		{
			"offsets": [
				184,
				517
			],
			"loop": false,
			"anim": "singLEFT",
			"fps": 24,
			"name": "Bon NOTE LEFT0",
			"indices": []
		},
		{
			"offsets": [
				137,
				502
			],
			"loop": false,
			"anim": "singRIGHT",
			"fps": 24,
			"name": "Bon Note Right0",
			"indices": []
		},
		{
			"offsets": [
				179,
				502
			],
			"loop": false,
			"anim": "singUP",
			"fps": 24,
			"name": "Bon Up note0",
			"indices": []
		},
		{
			"offsets": [
				190,
				502
			],
			"loop": false,
			"anim": "singDOWN",
			"fps": 24,
			"name": "Bon Down Note0",
			"indices": []
		}
	],
	"no_antialiasing": false,
	"image": "characters/PR_FNF_assets",
	"position": [
		0,
		300
	],
	"healthicon": "pr",
	"flip_x": true,
	"healthbar_colors": [
		225,
		137,
		30
	],
	"camera_position": [
		-30,
		-630
	],
	"sing_duration": 4,
	"scale": 1.1
}