<?xml version='1.0' encoding='utf-8'?>
<TextureAtlas imagePath="unbeta.png"><SubTexture name="unbeta idle0000" x="1712.5" y="0.0" width="897.5" height="816.0" frameX="-52.0" frameY="-46.0" frameWidth="960.0" frameHeight="960.0" />
<SubTexture name="unbeta idle0001" x="1712.5" y="816.0" width="885.0" height="816.0" frameX="-65.5" frameY="-117.5" frameWidth="960.0" frameHeight="960.0" />
<SubTexture name="unbeta idle0002" x="0.0" y="1644.0" width="887.5" height="816.0" frameX="-60.0" frameY="-116.5" frameWidth="960.0" frameHeight="960.0" />
<SubTexture name="unbeta idle0003" x="887.5" y="1644.0" width="893.5" height="816.0" frameX="-56.0" frameY="-52.0" frameWidth="960.0" frameHeight="960.0" />
<SubTexture name="unbeta left0000" x="2610.0" y="0.0" width="863.5" height="816.0" frameX="-52.0" frameY="-46.0" frameWidth="960.0" frameHeight="960.0" />
<SubTexture name="unbeta left0001" x="0.0" y="2460.0" width="881.0" height="816.0" frameX="-52.0" frameY="-46.0" frameWidth="960.0" frameHeight="960.0" />
<SubTexture name="unbeta left0002" x="881.0" y="2460.0" width="904.5" height="816.0" frameX="-52.0" frameY="-46.0" frameWidth="960.0" frameHeight="960.0" />
<SubTexture name="unbeta left0003" x="1785.5" y="2460.0" width="904.0" height="816.0" frameX="-52.0" frameY="-46.0" frameWidth="960.0" frameHeight="960.0" />
<SubTexture name="unbeta right0000" x="3473.5" y="0.0" width="890.5" height="816.0" frameX="-52.0" frameY="-46.0" frameWidth="960.0" frameHeight="960.0" />
<SubTexture name="unbeta right0001" x="3473.5" y="816.0" width="806.5" height="816.0" frameX="-52.0" frameY="-46.0" frameWidth="960.0" frameHeight="960.0" />
<SubTexture name="unbeta right0002" x="3473.5" y="1632.0" width="816.5" height="816.0" frameX="-52.0" frameY="-46.0" frameWidth="960.0" frameHeight="960.0" />
<SubTexture name="unbeta right0003" x="3473.5" y="2448.0" width="819.5" height="816.0" frameX="-52.0" frameY="-46.0" frameWidth="960.0" frameHeight="960.0" />
<SubTexture name="unbeta up0000" x="0.0" y="3276.0" width="877.5" height="816.0" frameX="-52.0" frameY="-46.0" frameWidth="960.0" frameHeight="960.0" />
<SubTexture name="unbeta up0001" x="2610.0" y="816.0" width="856.0" height="816.0" frameX="-52.0" frameY="-46.0" frameWidth="960.0" frameHeight="960.0" />
<SubTexture name="unbeta up0002" x="2610.0" y="1632.0" width="862.0" height="816.0" frameX="-52.0" frameY="-46.0" frameWidth="960.0" frameHeight="960.0" />
<SubTexture name="unbeta up0003" x="877.5" y="3276.0" width="868.0" height="816.0" frameX="-52.0" frameY="-46.0" frameWidth="960.0" frameHeight="960.0" />
<SubTexture name="unbeta down0000" x="1745.5" y="3276.0" width="898.5" height="816.0" frameX="-52.0" frameY="-46.0" frameWidth="960.0" frameHeight="960.0" />
<SubTexture name="unbeta down0001" x="0.0" y="0.0" width="906.0" height="827.0" frameX="-52.0" frameY="-46.0" frameWidth="960.0" frameHeight="960.0" />
<SubTexture name="unbeta down0002" x="0.0" y="827.0" width="898.5" height="817.0" frameX="-52.0" frameY="-46.0" frameWidth="960.0" frameHeight="960.0" />
<SubTexture name="unbeta down0003" x="2644.0" y="3276.0" width="900.5" height="816.0" frameX="-52.0" frameY="-46.0" frameWidth="960.0" frameHeight="960.0" />
<SubTexture name="unbeta alt left0000" x="4364.0" y="0.0" width="896.5" height="816.0" frameX="-53.0" frameY="-56.0" frameWidth="960.0" frameHeight="960.0" />
<SubTexture name="unbeta alt left0001" x="0.0" y="4092.0" width="947.0" height="816.0" frameX="-2.5" frameY="-85.0" frameWidth="960.0" frameHeight="960.0" />
<SubTexture name="unbeta alt left0002" x="947.0" y="4092.0" width="947.5" height="816.0" frameX="-2.0" frameY="-85.0" frameWidth="960.0" frameHeight="960.0" />
<SubTexture name="unbeta alt left0003" x="1894.5" y="4092.0" width="910.0" height="816.0" frameX="-39.5" frameY="-62.0" frameWidth="960.0" frameHeight="960.0" />
<SubTexture name="unbeta alt right0000" x="4364.0" y="816.0" width="867.0" height="816.0" frameX="-82.5" frameY="-70.0" frameWidth="960.0" frameHeight="960.0" />
<SubTexture name="unbeta alt right0001" x="898.5" y="827.0" width="806.5" height="816.5" frameX="-143.0" frameY="-43.0" frameWidth="960.0" frameHeight="960.0" />
<SubTexture name="unbeta alt right0002" x="906.0" y="0.0" width="806.5" height="818.0" frameX="-143.0" frameY="-40.5" frameWidth="960.0" frameHeight="960.0" />
<SubTexture name="unbeta alt right0003" x="4364.0" y="1632.0" width="827.5" height="816.0" frameX="-122.0" frameY="-51.5" frameWidth="960.0" frameHeight="960.0" />
<SubTexture name="unbeta alt up0000" x="5260.5" y="2040.0" width="909.0" height="622.5" frameX="-40.5" frameY="-95.0" frameWidth="960.0" frameHeight="960.0" />
<SubTexture name="unbeta alt up0001" x="2804.5" y="4092.0" width="942.0" height="729.5" frameX="-7.5" frameY="-2.0" frameWidth="960.0" frameHeight="960.0" />
<SubTexture name="unbeta alt up0002" x="3746.5" y="4092.0" width="949.0" height="727.0" frameX="-0.5" frameY="-2.0" frameWidth="960.0" frameHeight="960.0" />
<SubTexture name="unbeta alt up0003" x="5260.5" y="0.0" width="949.5" height="715.0" frameX="0.0" frameY="-9.0" frameWidth="960.0" frameHeight="960.0" />
<SubTexture name="unbeta alt down0000" x="5260.5" y="715.0" width="891.0" height="679.5" frameX="-58.5" frameY="-228.5" frameWidth="960.0" frameHeight="960.0" />
<SubTexture name="unbeta alt down0001" x="5260.5" y="1394.5" width="925.0" height="645.5" frameX="-24.5" frameY="-238.0" frameWidth="960.0" frameHeight="960.0" />
<SubTexture name="unbeta alt down0002" x="5260.5" y="3249.0" width="921.5" height="586.0" frameX="-28.0" frameY="-240.5" frameWidth="960.0" frameHeight="960.0" />
<SubTexture name="unbeta alt down0003" x="5260.5" y="2662.5" width="922.5" height="586.5" frameX="-27.0" frameY="-261.0" frameWidth="960.0" frameHeight="960.0" />
</TextureAtlas>
