<?xml version="1.0" encoding="UTF-8"?>
<!--
Created with Free texture packer v0.6.7 http://free-tex-packer.com
-->
<TextureAtlas imagePath="Logo bumpin.png" width="826" height="3520">
  <SubTexture name="logo bumpin0000.png" x="2" y="2"  width="822" height="700" frameX="-0" frameY="-0" frameWidth="822" frameHeight="700"/>
  <SubTexture name="logo bumpin0001.png" x="2" y="2"  width="822" height="700" frameX="-0" frameY="-0" frameWidth="822" frameHeight="700"/>
  <SubTexture name="logo bumpin0002.png" x="2" y="706"  width="822" height="700" frameX="-0" frameY="-0" frameWidth="822" frameHeight="700"/>
  <SubTexture name="logo bumpin0003.png" x="2" y="706"  width="822" height="700" frameX="-0" frameY="-0" frameWidth="822" frameHeight="700"/>
  <SubTexture name="logo bumpin0004.png" x="2" y="1410"  width="822" height="700" frameX="-0" frameY="-0" frameWidth="822" frameHeight="700"/>
  <SubTexture name="logo bumpin0005.png" x="2" y="1410"  width="822" height="700" frameX="-0" frameY="-0" frameWidth="822" frameHeight="700"/>
  <SubTexture name="logo bumpin0006.png" x="2" y="2114"  width="822" height="700" frameX="-0" frameY="-0" frameWidth="822" frameHeight="700"/>
  <SubTexture name="logo bumpin0007.png" x="2" y="2114"  width="822" height="700" frameX="-0" frameY="-0" frameWidth="822" frameHeight="700"/>
  <SubTexture name="logo bumpin0008.png" x="2" y="2818"  width="822" height="700" frameX="-0" frameY="-0" frameWidth="822" frameHeight="700"/>
  <SubTexture name="logo bumpin0009.png" x="2" y="2818"  width="822" height="700" frameX="-0" frameY="-0" frameWidth="822" frameHeight="700"/>
</TextureAtlas>