<?xml version="1.0" encoding="utf-8"?>
<TextureAtlas imagePath="bfpuppet2.png">
	<!-- Created with Adobe Animate version 20.5.1.31044 -->
	<!-- http://www.adobe.com/products/animate.html -->
	<SubTexture name="BF NOTE DOWN0000" x="0" y="0" width="595" height="576" pivotX="0" pivotY="43" frameX="0" frameY="-43" frameWidth="595" frameHeight="619"/>
	<SubTexture name="BF NOTE DOWN0001" x="595" y="0" width="595" height="583" frameX="0" frameY="-36" frameWidth="595" frameHeight="619"/>
	<SubTexture name="BF NOTE DOWN0002" x="1190" y="0" width="595" height="597" frameX="0" frameY="-22" frameWidth="595" frameHeight="619"/>
	<SubTexture name="BF NOTE DOWN0003" x="1785" y="0" width="594" height="608" frameX="0" frameY="-11" frameWidth="595" frameHeight="619"/>
	<SubTexture name="BF NOTE DOWN0004" x="2379" y="0" width="594" height="615" frameX="0" frameY="-4" frameWidth="595" frameHeight="619"/>
	<SubTexture name="BF NOTE DOWN0005" x="2973" y="0" width="594" height="618" frameX="0" frameY="-1" frameWidth="595" frameHeight="619"/>
	<SubTexture name="BF NOTE DOWN0006" x="3567" y="0" width="594" height="619" frameX="0" frameY="0" frameWidth="595" frameHeight="619"/>
	<SubTexture name="BF NOTE DOWN0007" x="4161" y="0" width="594" height="618" frameX="0" frameY="-1" frameWidth="595" frameHeight="619"/>
	<SubTexture name="BF NOTE LEFT0000" x="4755" y="0" width="581" height="600" pivotX="0" pivotY="28" frameX="0" frameY="-28" frameWidth="612" frameHeight="628"/>
	<SubTexture name="BF NOTE LEFT0001" x="0" y="619" width="589" height="605" frameX="0" frameY="-23" frameWidth="612" frameHeight="628"/>
	<SubTexture name="BF NOTE LEFT0002" x="589" y="619" width="603" height="614" frameX="0" frameY="-14" frameWidth="612" frameHeight="628"/>
	<SubTexture name="BF NOTE LEFT0003" x="1192" y="619" width="610" height="622" frameX="0" frameY="-6" frameWidth="612" frameHeight="628"/>
	<SubTexture name="BF NOTE LEFT0004" x="1802" y="619" width="612" height="625" frameX="0" frameY="-3" frameWidth="612" frameHeight="628"/>
	<SubTexture name="BF NOTE LEFT0005" x="2414" y="619" width="612" height="627" frameX="0" frameY="-1" frameWidth="612" frameHeight="628"/>
	<SubTexture name="BF NOTE LEFT0006" x="3026" y="619" width="611" height="628" frameX="0" frameY="0" frameWidth="612" frameHeight="628"/>
	<SubTexture name="BF NOTE LEFT0007" x="3637" y="619" width="611" height="628" frameX="0" frameY="0" frameWidth="612" frameHeight="628"/>
	<SubTexture name="BF NOTE RIGHT0000" x="4248" y="619" width="585" height="648" pivotX="0" pivotY="6" frameX="0" frameY="-7" frameWidth="594" frameHeight="655"/>
	<SubTexture name="BF NOTE RIGHT0001" x="4833" y="619" width="586" height="650" frameX="0" frameY="-5" frameWidth="594" frameHeight="655"/>
	<SubTexture name="BF NOTE RIGHT0002" x="0" y="1269" width="590" height="651" frameX="0" frameY="-4" frameWidth="594" frameHeight="655"/>
	<SubTexture name="BF NOTE RIGHT0003" x="590" y="1269" width="592" height="653" frameX="0" frameY="-2" frameWidth="594" frameHeight="655"/>
	<SubTexture name="BF NOTE RIGHT0004" x="1182" y="1269" width="593" height="654" frameX="0" frameY="-1" frameWidth="594" frameHeight="655"/>
	<SubTexture name="BF NOTE RIGHT0005" x="1775" y="1269" width="594" height="654" frameX="0" frameY="-1" frameWidth="594" frameHeight="655"/>
	<SubTexture name="BF NOTE RIGHT0006" x="2369" y="1269" width="594" height="655"/>
	<SubTexture name="BF NOTE RIGHT0007" x="2963" y="1269" width="594" height="655"/>
	<SubTexture name="BF NOTE UP0000" x="3557" y="1269" width="618" height="646" pivotX="0" pivotY="10" frameX="-1" frameY="-10" frameWidth="632" frameHeight="656"/>
	<SubTexture name="BF NOTE UP0001" x="4175" y="1269" width="620" height="647" frameX="0" frameY="-9" frameWidth="632" frameHeight="656"/>
	<SubTexture name="BF NOTE UP0002" x="4795" y="1269" width="624" height="651" frameX="0" frameY="-5" frameWidth="632" frameHeight="656"/>
	<SubTexture name="BF NOTE UP0003" x="0" y="1924" width="627" height="653" frameX="0" frameY="-2" frameWidth="632" frameHeight="656"/>
	<SubTexture name="BF NOTE UP0004" x="627" y="1924" width="628" height="655" frameX="0" frameY="-1" frameWidth="632" frameHeight="656"/>
	<SubTexture name="BF NOTE UP0005" x="1255" y="1924" width="630" height="656" frameX="0" frameY="0" frameWidth="632" frameHeight="656"/>
	<SubTexture name="BF NOTE UP0006" x="1885" y="1924" width="632" height="656"/>
	<SubTexture name="BF NOTE UP0007" x="2517" y="1924" width="632" height="656"/>
	<SubTexture name="BF idle dance0000" x="3149" y="1924" width="601" height="660" pivotX="0" pivotY="0" frameX="0" frameY="0" frameWidth="601" frameHeight="661"/>
	<SubTexture name="BF idle dance0001" x="3750" y="1924" width="600" height="659" frameX="0" frameY="-1" frameWidth="601" frameHeight="661"/>
	<SubTexture name="BF idle dance0002" x="4350" y="1924" width="599" height="657" frameX="0" frameY="-3" frameWidth="601" frameHeight="661"/>
	<SubTexture name="BF idle dance0003" x="0" y="2584" width="598" height="655" frameX="0" frameY="-4" frameWidth="601" frameHeight="661"/>
	<SubTexture name="BF idle dance0004" x="598" y="2584" width="595" height="654" frameX="0" frameY="-6" frameWidth="601" frameHeight="661"/>
	<SubTexture name="BF idle dance0005" x="1193" y="2584" width="596" height="654" frameX="0" frameY="-6" frameWidth="601" frameHeight="661"/>
	<SubTexture name="BF idle dance0006" x="1789" y="2584" width="595" height="654" frameX="0" frameY="-7" frameWidth="601" frameHeight="661"/>
	<SubTexture name="BF idle dance0007" x="2384" y="2584" width="594" height="654" frameX="0" frameY="-6" frameWidth="601" frameHeight="661"/>
	<SubTexture name="BF idle dance0008" x="2978" y="2584" width="594" height="655" frameX="0" frameY="-5" frameWidth="601" frameHeight="661"/>
	<SubTexture name="BF idle dance0009" x="3572" y="2584" width="598" height="658" frameX="0" frameY="-1" frameWidth="601" frameHeight="661"/>
	<SubTexture name="BF idle dance0010" x="4170" y="2584" width="601" height="660" frameX="0" frameY="0" frameWidth="601" frameHeight="661"/>
</TextureAtlas>
