{
	"animations": [
		{
			"loop": false,
			"offsets": [
				0,
				0
			],
			"anim": "singLEFT",
			"fps": 24,
			"name": "mario left",
			"indices": []
		},
		{
			"loop": false,
			"offsets": [
				0,
				0
			],
			"anim": "singDOWN",
			"fps": 24,
			"name": "mario down",
			"indices": []
		},
		{
			"loop": false,
			"offsets": [
				0,
				0
			],
			"anim": "singUP",
			"fps": 24,
			"name": "mario up",
			"indices": []
		},
		{
			"loop": false,
			"offsets": [
				0,
				0
			],
			"anim": "singRIGHT",
			"fps": 24,
			"name": "mario right",
			"indices": []
		},
		{
			"loop": false,
			"offsets": [
				0,
				0
			],
			"anim": "idle",
			"fps": 24,
			"name": "mario idle",
			"indices": []
		}
	],
	"no_antialiasing": false,
	"image": "characters/mario_phantomart",
	"position": [
		-60,
		190
	],
	"healthicon": "oreo",
	"flip_x": false,
	"healthbar_colors": [
		255,
		0,
		0
	],
	"camera_position": [
		-130,
		10
	],
	"sing_duration": 6.1,
	"scale": 1
}