{
	"animations": [
		{
			"offsets": [
				0,
				0
			],
			"loop": false,
			"fps": 24,
			"anim": "idle",
			"indices": [],
			"name": "idlefart0"
		},
		{
			"offsets": [
				24,
				8
			],
			"loop": false,
			"fps": 24,
			"anim": "singUP",
			"indices": [],
			"name": "upfart0"
		},
		{
			"offsets": [
				44,
				2
			],
			"loop": false,
			"fps": 24,
			"anim": "singRIGHT",
			"indices": [],
			"name": "rightfart0"
		},
		{
			"loop": false,
			"offsets": [
				49,
				-8
			],
			"anim": "singDOWN",
			"fps": 24,
			"name": "downfart0",
			"indices": []
		},
		{
			"loop": false,
			"offsets": [
				96,
				0
			],
			"anim": "singLEFT",
			"fps": 24,
			"name": "leftfaart0",
			"indices": []
		}
	],
	"vocals_file": "",
	"no_antialiasing": true,
	"image": "characters/knifemuffin",
	"position": [
		1510,
		910
	],
	"healthicon": "muffin",
	"flip_x": true,
	"healthbar_colors": [
		255,
		255,
		255
	],
	"camera_position": [
		-110,
		-20
	],
	"sing_duration": 6.1,
	"scale": 1.3,
	"_editor_isPlayer": true
}