{
	"animations": [
		{
			"loop": false,
			"offsets": [
				-3,
				98
			],
			"anim": "idle",
			"fps": 24,
			"name": "BowserBF idle",
			"indices": []
		},
		{
			"loop": false,
			"offsets": [
				-15,
				143
			],
			"anim": "singDOWN",
			"fps": 24,
			"name": "BowserBF down",
			"indices": []
		},
		{
			"loop": false,
			"offsets": [
				-13,
				127
			],
			"anim": "singUP",
			"fps": 24,
			"name": "BowserBF up",
			"indices": []
		},
		{
			"loop": false,
			"offsets": [
				-18,
				140
			],
			"anim": "singDOWNmiss",
			"fps": 24,
			"name": "down miss",
			"indices": []
		},
		{
			"loop": false,
			"offsets": [
				-16,
				120
			],
			"anim": "singUPmiss",
			"fps": 24,
			"name": "up miss",
			"indices": []
		},
		{
			"loop": false,
			"offsets": [
				-10,
				97
			],
			"anim": "singRIGHTmiss",
			"fps": 24,
			"name": "right miss",
			"indices": []
		},
		{
			"loop": false,
			"offsets": [
				215,
				612
			],
			"anim": "firstDeath",
			"fps": 24,
			"name": "BowserBF death",
			"indices": []
		},
		{
			"loop": false,
			"offsets": [
				217,
				619
			],
			"anim": "bap",
			"fps": 24,
			"name": "BowserBF death",
			"indices": [
				0,
				1,
				2,
				3,
				4,
				5,
				6,
				7,
				8,
				9
			]
		},
		{
			"offsets": [
				-48,
				104
			],
			"loop": false,
			"fps": 24,
			"anim": "singRIGHT",
			"indices": [],
			"name": "BowserBF left"
		},
		{
			"offsets": [
				-1,
				99
			],
			"loop": false,
			"fps": 24,
			"anim": "singLEFT",
			"indices": [],
			"name": "BowserBF right"
		},
		{
			"offsets": [
				-2,
				100
			],
			"loop": false,
			"fps": 24,
			"anim": "singLEFTmiss",
			"indices": [],
			"name": "right miss"
		}
	],
	"no_antialiasing": false,
	"image": "characters/BowserBF",
	"position": [
		-200,
		910
	],
	"healthicon": "bbfbgf",
	"flip_x": false,
	"healthbar_colors": [
		255,
		0,
		0
	],
	"camera_position": [
		-630,
		-550
	],
	"sing_duration": 4,
	"scale": 0.8
}